satorisynapse/__init__.py
satorisynapse/run.py
satorisynapse/lib/__init__.py
satorisynapse/lib/domain.py
satorisynapse/lib/error.py
satorisynapse/lib/requests.py
satorisynapse/lib/utils.py
satorisynapse/synapse/__init__.py
satorisynapse/synapse/asynchronous.py
satorisynapse/synapse/threaded.py
satorisynapse-0.1.3.dist-info/LICENSE
satorisynapse-0.1.3.dist-info/METADATA
satorisynapse-0.1.3.dist-info/WHEEL
satorisynapse-0.1.3.dist-info/dependency_links.txt
satorisynapse-0.1.3.dist-info/entry_points.txt
satorisynapse-0.1.3.dist-info/top_level.txt
satorisynapse-0.1.3.dist-info/RECORD
