Metadata-Version: 2.1
Name: satorisynapse
Version: 0.1.3
Summary: satorisynapse contains domain model and apis for the Satori Network
Home-page: https://github.com/SatoriNetwork/satorisynapse
Download-URL: https://github.com/SatoriNetwork/satorisynapse
Author: Jordan Miller
Author-email: jordan@satorinet.io
Classifier: Programming Language :: Python :: 3
Classifier: License :: OSI Approved :: Apache Software License
Classifier: Operating System :: OS Independent
Requires-Python: >=3.7
License-File: LICENSE
